nullscream/__init__.py
nullscream/noop_class.py
nullscream/noop_function.py
nullscream-0.1.5.dist-info/licenses/LICENSE
nullscream-0.1.5.dist-info/METADATA
nullscream-0.1.5.dist-info/WHEEL
nullscream-0.1.5.dist-info/top_level.txt
nullscream-0.1.5.dist-info/RECORD
