Metadata-Version: 2.4
Name: nullscream
Version: 0.1.5
Home-page: https://github.com/Capsize-Games/nullscream
Author: Capsize LLC
Author-email: contact@capsizegames.com
License: GPL-3.0
Requires-Python: >=3.10.0
License-File: LICENSE
Dynamic: author
Dynamic: author-email
Dynamic: description
Dynamic: description-content-type
Dynamic: home-page
Dynamic: keywords
Dynamic: license
Dynamic: license-file
Dynamic: requires-python
